avm_client/__init__.py
avm_client/api_client.py
avm_client/configuration.py
avm_client/exceptions.py
avm_client/rest.py
avm_client/api/__init__.py
avm_client/api/default_api.py
avm_client/models/__init__.py
avm_client/models/additional_features.py
avm_client/models/built_form.py
avm_client/models/energy_efficiency.py
avm_client/models/energy_rating.py
avm_client/models/floor_level.py
avm_client/models/leasehold_or_freehold.py
avm_client/models/new_or_resale.py
avm_client/models/problem.py
avm_client/models/property_features.py
avm_client/models/property_type.py
avm_client/models/required_features.py
avm_client/models/roof_insulation.py
avm_client/models/roof_type.py
avm_client/models/valuation.py
avm_client/models/valuation_price_distribution.py
avm_client/models/wall_insulation.py
avm_client/models/wall_type.py
avm_client/models/window_glazing_type.py
avm_client-1.0.3.dist-info/LICENSE
avm_client-1.0.3.dist-info/METADATA
avm_client-1.0.3.dist-info/WHEEL
avm_client-1.0.3.dist-info/top_level.txt
avm_client-1.0.3.dist-info/RECORD
